audiobook/__init__.py
audiobook/cli.py
audiobook/config.py
audiobook/main.py
audiobook/utils.py
audiobook/doc_parser/__init__.py
audiobook/doc_parser/pdf_parser.py
audiobook/doc_parser/web_parser.py
audiobook-3.0.5.dist-info/licenses/LICENSE
tests/__init__.py
tests/test_create_json_book.py
audiobook-3.0.5.dist-info/METADATA
audiobook-3.0.5.dist-info/WHEEL
audiobook-3.0.5.dist-info/entry_points.txt
audiobook-3.0.5.dist-info/top_level.txt
audiobook-3.0.5.dist-info/RECORD
