Metadata-Version: 2.4
Name: audiobook
Version: 3.0.5
Summary: Listen to your favourite audiobook
Home-page: https://github.com/Py-Contributors/audiobook
Author: CodePerfectPlus
Author-email: deepak008@live.com
Project-URL: Documentation, https://pycontributors.readthedocs.io/projects/Audiobook/en/latest/
Project-URL: Source, https://github.com/Py-Contributors/AudioBook
Project-URL: Tracker, https://github.com/Py-Contributors/AudioBook/issues
Keywords: audiobook
Classifier: Development Status :: 5 - Production/Stable
Classifier: Programming Language :: Python :: 3
Classifier: License :: OSI Approved :: MIT License
Classifier: Operating System :: OS Independent
Classifier: Intended Audience :: End Users/Desktop
Classifier: Intended Audience :: Developers
Requires-Python: >=3.4
License-File: LICENSE
Requires-Dist: pyttsx3==2.98
Requires-Dist: PyPDF2==3.0.1
Requires-Dist: ebooklib==0.19
Requires-Dist: beautifulsoup4==4.13.4
Requires-Dist: html2text==2025.4.15
Requires-Dist: mobi==0.3.3
Requires-Dist: docx2txt==0.9
Requires-Dist: requests==2.32.3
Requires-Dist: tqdm==4.67.1
Requires-Dist: pdfminer==20191125
Requires-Dist: defusedxml==0.7.1
Requires-Dist: odfpy==1.4.1
Requires-Dist: pytest==8.3.5
Requires-Dist: flake8==7.2.0
Requires-Dist: striprtf==0.0.29
Dynamic: author
Dynamic: author-email
Dynamic: classifier
Dynamic: description
Dynamic: description-content-type
Dynamic: home-page
Dynamic: keywords
Dynamic: license-file
Dynamic: project-url
Dynamic: requires-dist
Dynamic: requires-python
Dynamic: summary
